scitacean/__init__.py
scitacean/_base_model.py
scitacean/_dataset_fields.py
scitacean/_profile.py
scitacean/client.py
scitacean/datablock.py
scitacean/dataset.py
scitacean/error.py
scitacean/file.py
scitacean/filesystem.py
scitacean/logging.py
scitacean/model.py
scitacean/pid.py
scitacean/py.typed
scitacean/thumbnail.py
scitacean/typing.py
scitacean/warning.py
scitacean/_html_repr/__init__.py
scitacean/_html_repr/_attachment_html.py
scitacean/_html_repr/_common_html.py
scitacean/_html_repr/_dataset_html.py
scitacean/_html_repr/_resources.py
scitacean/_html_repr/images/__init__.py
scitacean/_html_repr/images/lock.svg
scitacean/_html_repr/styles/__init__.py
scitacean/_html_repr/styles/attachment.css
scitacean/_html_repr/styles/common.css
scitacean/_html_repr/styles/dataset.css
scitacean/_html_repr/templates/__init__.py
scitacean/_html_repr/templates/attachment_field_repr.html.template
scitacean/_html_repr/templates/attachment_repr.html.template
scitacean/_html_repr/templates/dataset_field_repr.html.template
scitacean/_html_repr/templates/dataset_repr.html.template
scitacean/_html_repr/templates/files_repr.html.template
scitacean/_html_repr/templates/metadata_repr.html.template
scitacean/_internal/__init__.py
scitacean/_internal/docker.py
scitacean/_internal/file_counter.py
scitacean/_internal/jwt.py
scitacean/_internal/orcid.py
scitacean/testing/__init__.py
scitacean/testing/_pytest_helpers.py
scitacean/testing/client.py
scitacean/testing/docs.py
scitacean/testing/strategies.py
scitacean/testing/transfer.py
scitacean/testing/backend/__init__.py
scitacean/testing/backend/_backend.py
scitacean/testing/backend/_pytest_helpers.py
scitacean/testing/backend/config.py
scitacean/testing/backend/docker-compose-backend-template.yaml
scitacean/testing/backend/fixtures.py
scitacean/testing/backend/seed.py
scitacean/testing/sftp/Dockerfile-sftp-server
scitacean/testing/sftp/__init__.py
scitacean/testing/sftp/_pytest_helpers.py
scitacean/testing/sftp/_sftp.py
scitacean-25.8.0.dist-info/licenses/LICENSE
scitacean-25.8.0.dist-info/METADATA
scitacean-25.8.0.dist-info/WHEEL
scitacean-25.8.0.dist-info/top_level.txt
scitacean-25.8.0.dist-info/RECORD
