Metadata-Version: 2.4
Name: scitacean
Version: 25.8.0
Summary: High-level interface for SciCat
Author: Scitacean contributors
License-Expression: BSD-3-Clause
Project-URL: Documentation, https://scicatproject.github.io/scitacean
Project-URL: Bug Tracker, https://github.com/SciCatProject/scitacean/issues
Project-URL: Source, https://github.com/SciCatProject/scitacean
Keywords: scicat
Classifier: Development Status :: 5 - Production/Stable
Classifier: Intended Audience :: Science/Research
Classifier: Natural Language :: English
Classifier: Operating System :: OS Independent
Classifier: Programming Language :: Python :: 3
Classifier: Programming Language :: Python :: 3 :: Only
Classifier: Programming Language :: Python :: 3.10
Classifier: Programming Language :: Python :: 3.11
Classifier: Programming Language :: Python :: 3.12
Classifier: Programming Language :: Python :: 3.13
Classifier: Topic :: Scientific/Engineering
Classifier: Typing :: Typed
Requires-Python: >=3.10
License-File: LICENSE
Requires-Dist: email-validator>=2
Requires-Dist: httpx>=0.24
Requires-Dist: pydantic>=2
Requires-Dist: python-dateutil>=2.8
Requires-Dist: tomli>=2.2.0
Provides-Extra: sftp
Requires-Dist: paramiko>=3; extra == "sftp"
Provides-Extra: test
Requires-Dist: filelock>=3; extra == "test"
Requires-Dist: hypothesis>=6.48; extra == "test"
Requires-Dist: pyyaml>=5; extra == "test"
Dynamic: license-file
